txredisapi.py
txredisapi-1.4.10.dist-info/LICENSE
txredisapi-1.4.10.dist-info/METADATA
txredisapi-1.4.10.dist-info/WHEEL
txredisapi-1.4.10.dist-info/top_level.txt
txredisapi-1.4.10.dist-info/RECORD
